{
  "collapse-filter": false,
  "search": "-path:daily_note",
  "showTags": false,
  "showAttachments": false,
  "hideUnresolved": true,
  "showOrphans": true,
  "collapse-color-groups": false,
  "colorGroups": [
    {
      "query": "-path:post",
      "color": {
        "a": 1,
        "rgb": 4539717
      }
    },
    {
      "query": "file:_post",
      "color": {
        "a": 1,
        "rgb": 14701138
      }
    },
    {
      "query": "file:_",
      "color": {
        "a": 1,
        "rgb": 3826916
      }
    }
  ],
  "collapse-display": false,
  "showArrow": true,
  "textFadeMultiplier": 0.4,
  "nodeSizeMultiplier": 1.32772974418397,
  "lineSizeMultiplier": 1.05526315789474,
  "collapse-forces": false,
  "centerStrength": 0.750601657901774,
  "repelStrength": 14.2359144614784,
  "linkStrength": 0.927667350031197,
  "linkDistance": 95,
  "scale": 1.0534979423868018,
  "close": true
}